LICENSE
MANIFEST.in
README.md
setup.py
django_theherk_download.egg-info/PKG-INFO
django_theherk_download.egg-info/SOURCES.txt
django_theherk_download.egg-info/dependency_links.txt
django_theherk_download.egg-info/top_level.txt
download/__init__.py
download/cms_plugins.py
download/models.py
download/migrations/0001_initial.py
download/migrations/__init__.py
download/templates/download/plugin.html