Metadata-Version: 1.1
Name: django-theherk-download
Version: 1.2
Summary: Django CMS plugin to post a download link
Home-page: https://github.com/theherk/django-theherk-download
Author: Adam Sherwood
Author-email: theherk@gmail.com
License: see file LICENSE
Platform: UNKNOWN
Classifier: Environment :: Web Environment
Classifier: Framework :: Django
Classifier: Intended Audience :: Developers
Classifier: Operating System :: OS Independent
Classifier: Programming Language :: Python
Classifier: Programming Language :: Python :: 2.6
Classifier: Programming Language :: Python :: 2.7
Classifier: Topic :: Internet :: WWW/HTTP
Classifier: Topic :: Internet :: WWW/HTTP :: Dynamic Content
